odoo/addons/ssi_stock_rent_operation/README.rst
odoo/addons/ssi_stock_rent_operation/__init__.py
odoo/addons/ssi_stock_rent_operation/__manifest__.py
odoo/addons/ssi_stock_rent_operation/data/ir_property_data.xml
odoo/addons/ssi_stock_rent_operation/data/location_type_data.xml
odoo/addons/ssi_stock_rent_operation/data/stock_location_data.xml
odoo/addons/ssi_stock_rent_operation/data/stock_picking_type_category_data.xml
odoo/addons/ssi_stock_rent_operation/models/__init__.py
odoo/addons/ssi_stock_rent_operation/models/res_partner.py
odoo/addons/ssi_stock_rent_operation/security/ir_module_category_data.xml
odoo/addons/ssi_stock_rent_operation/security/res_group_data.xml
odoo/addons/ssi_stock_rent_operation/static/description/icon.png
odoo/addons/ssi_stock_rent_operation/views/customer_rent_in_views.xml
odoo/addons/ssi_stock_rent_operation/views/customer_rent_out_views.xml
odoo/addons/ssi_stock_rent_operation/views/res_partner_views.xml
odoo/addons/ssi_stock_rent_operation/views/supplier_rent_in_views.xml
odoo/addons/ssi_stock_rent_operation/views/supplier_rent_out_views.xml
odoo14_addon_ssi_stock_rent_operation-14.0.1.1.0.dist-info/METADATA
odoo14_addon_ssi_stock_rent_operation-14.0.1.1.0.dist-info/WHEEL
odoo14_addon_ssi_stock_rent_operation-14.0.1.1.0.dist-info/top_level.txt
odoo14_addon_ssi_stock_rent_operation-14.0.1.1.0.dist-info/RECORD
